py_localtunnel/__init__.py
py_localtunnel/cli.py
py_localtunnel/get_assigned_url.py
py_localtunnel/tunnel.py
py_localtunnel-1.0.1.dist-info/LICENSE
py_localtunnel-1.0.1.dist-info/METADATA
py_localtunnel-1.0.1.dist-info/WHEEL
py_localtunnel-1.0.1.dist-info/entry_points.txt
py_localtunnel-1.0.1.dist-info/top_level.txt
py_localtunnel-1.0.1.dist-info/RECORD
