Metadata-Version: 2.1
Name: py-localtunnel
Version: 1.0.1
Summary: localtunnel alternative in python
Home-page: https://github.com/jakbin/py-localtunnel
Author: Jak Bin
Author-email: jakbin4747@gmail.com
Project-URL: Bug Tracker, https://github.com/jakbin/py-localtunnel/issues
Keywords: localtunnel,port-forwarding,expose-locahost,localtunnel
Classifier: Programming Language :: Python :: 3.6
Classifier: License :: OSI Approved :: MIT License
Classifier: Natural Language :: English
Classifier: Operating System :: OS Independent
Requires-Python: >=3
License-File: LICENSE
Requires-Dist: urllib3
